setup.py
data_importer/__init__.py
data_importer/base.py
data_importer/exceptions.py
data_importer/handlers.py
data_importer/models.py
data_importer/utils.py
data_importer/readers/__init__.py
data_importer/readers/base.py
data_importer/readers/csv_reader.py
data_importer/readers/xls_reader.py
data_importer/tests/__init__.py
data_importer/tests/cpfcnpj.py
data_importer/tests/importers.py
data_importer/tests/mocks.py
data_importer/tests/models.py
data_importer/tests/test_base.py
django_data_importer_jl.egg-info/PKG-INFO
django_data_importer_jl.egg-info/SOURCES.txt
django_data_importer_jl.egg-info/dependency_links.txt
django_data_importer_jl.egg-info/not-zip-safe
django_data_importer_jl.egg-info/requires.txt
django_data_importer_jl.egg-info/top_level.txt
sampleproject/__init__.py
sampleproject/importer.py
sampleproject/manage.py
sampleproject/settings.py
sampleproject/urls.py
sampleproject/data_importer/__init__.py
sampleproject/data_importer/base.py
sampleproject/data_importer/exceptions.py
sampleproject/data_importer/handlers.py
sampleproject/data_importer/models.py
sampleproject/data_importer/utils.py
sampleproject/data_importer/readers/__init__.py
sampleproject/data_importer/readers/base.py
sampleproject/data_importer/readers/csv_reader.py
sampleproject/data_importer/readers/xls_reader.py
sampleproject/data_importer/tests/__init__.py
sampleproject/data_importer/tests/cpfcnpj.py
sampleproject/data_importer/tests/importers.py
sampleproject/data_importer/tests/mocks.py
sampleproject/data_importer/tests/models.py
sampleproject/data_importer/tests/test_base.py
sampleproject/sample/__init__.py
sampleproject/sample/br_cpfcnpj.py
sampleproject/sample/cpfcnpj.py
sampleproject/sample/models.py
sampleproject/sample/tests.py
sampleproject/sample/views.py